connectapi_core/__init__.py
connectapi_core/client.py
connectapi_core/exceptions.py
connectapi_core/singleton.py
connectapi_core-1.1.3.dist-info/LICENSE
connectapi_core-1.1.3.dist-info/METADATA
connectapi_core-1.1.3.dist-info/WHEEL
connectapi_core-1.1.3.dist-info/top_level.txt
connectapi_core-1.1.3.dist-info/RECORD
