Metadata-Version: 2.1
Name: connectapi-core
Version: 1.1.3
Summary: Core SDK for the ConnectAPI ecosystem
Home-page: https://github.com/ConnectAPI/python-core-client
Author: ConnectAPI
Author-email: connectapi.org@gmail.com
Maintainer: ConnectAPI
Maintainer-email: connectapi.org@gmail.com
License: MIT
Keywords: connectapi,ConnectAPI,web,client,core
Platform: UNKNOWN
Classifier: Development Status :: 5 - Production/Stable
Classifier: Intended Audience :: Developers
Classifier: Environment :: Web Environment
Classifier: Topic :: Software Development
Classifier: License :: OSI Approved :: MIT License
Classifier: Programming Language :: Python :: 3
Classifier: Programming Language :: Python :: 3.5
Classifier: Programming Language :: Python :: 3.6
Classifier: Programming Language :: Python :: 3.7
Classifier: Programming Language :: Python :: 3.8
License-File: LICENSE
Requires-Dist: requests
